{
  "performance": [
    {
      "tax_head": "customs",
      "model": "arimax",
      "h1_smape": 22.02,
      "h3_smape": 33.91,
      "h5_smape": 55.38,
      "mae_pct": 19.05,
      "rmse_pct": 22.42,
      "rmse_pct_abs": 16.43,
      "bias_pct": -12.46,
      "n_test": 14,
      "stability": 0.1182,
      "series": [
        {
          "actual": 239458.99999999997,
          "pred": 170641.78574590333
        },
        {
          "actual": 242810.9999999998,
          "pred": 212680.75599409733
        },
        {
          "actual": 306220.0,
          "pred": 197971.34036770297
        },
        {
          "actual": 404572.0,
          "pred": 210291.30313178222
        },
        {
          "actual": 496771.99999999994,
          "pred": 405224.8943743088
        },
        {
          "actual": 608373.0000000005,
          "pred": 531708.2040556774
        },
        {
          "actual": 685575.0000000001,
          "pred": 560996.5859467861
        },
        {
          "actual": 626612.0000000001,
          "pred": 469922.14894586016
        },
        {
          "actual": 748390.0000000001,
          "pred": 563315.3951491396
        },
        {
          "actual": 1010694.0,
          "pred": 1056522.6285067585
        },
        {
          "actual": 931727.0000000007,
          "pred": 795216.3137554225
        },
        {
          "actual": 1104066.0000000007,
          "pred": 1023571.7519026793
        },
        {
          "actual": 1284608.0000000005,
          "pred": 1370570.1384327228
        },
        {
          "actual": 1588000.0000000005,
          "pred": 1428450.201899793
        }
      ]
    },
    {
      "tax_head": "customs",
      "model": "enet",
      "h1_smape": 24.73,
      "h3_smape": 46.21,
      "h5_smape": 68.31,
      "mae_pct": 21.47,
      "rmse_pct": 23.64,
      "rmse_pct_abs": 19.4,
      "bias_pct": -17.6,
      "n_test": 14,
      "stability": 0.099,
      "series": [
        {
          "actual": 239458.99999999997,
          "pred": 171505.4086050912
        },
        {
          "actual": 242810.9999999998,
          "pred": 161883.94100884808
        },
        {
          "actual": 306220.0,
          "pred": 232702.82923705888
        },
        {
          "actual": 404572.0,
          "pred": 263133.0055658651
        },
        {
          "actual": 496771.99999999994,
          "pred": 325441.86699513206
        },
        {
          "actual": 608373.0000000005,
          "pred": 440447.7848285693
        },
        {
          "actual": 685575.0000000001,
          "pred": 539775.3378189255
        },
        {
          "actual": 626612.0000000001,
          "pred": 547604.98713711
        },
        {
          "actual": 748390.0000000001,
          "pred": 672144.4067550647
        },
        {
          "actual": 1010694.0,
          "pred": 717197.8346296671
        },
        {
          "actual": 931727.0000000007,
          "pred": 748266.2564017929
        },
        {
          "actual": 1104066.0000000007,
          "pred": 1016753.8046625028
        },
        {
          "actual": 1284608.0000000005,
          "pred": 1157424.3442018882
        },
        {
          "actual": 1588000.0000000005,
          "pred": 1474483.319601692
        }
      ]
    },
    {
      "tax_head": "customs",
      "model": "ardl",
      "h1_smape": 34.2,
      "h3_smape": 57.79,
      "h5_smape": 82.41,
      "mae_pct": 28.13,
      "rmse_pct": 31.3,
      "rmse_pct_abs": 33.91,
      "bias_pct": -26.43,
      "n_test": 14,
      "stability": 0.1373,
      "series": [
        {
          "actual": 239458.99999999997,
          "pred": 183231.4982829514
        },
        {
          "actual": 242810.9999999998,
          "pred": 145023.86618452411
        },
        {
          "actual": 306220.0,
          "pred": 197376.7653866737
        },
        {
          "actual": 404572.0,
          "pred": 245908.2604015434
        },
        {
          "actual": 496771.99999999994,
          "pred": 323040.7148708705
        },
        {
          "actual": 608373.0000000005,
          "pred": 422464.7968562685
        },
        {
          "actual": 685575.0000000001,
          "pred": 595832.8783730974
        },
        {
          "actual": 626612.0000000001,
          "pred": 403985.06872168323
        },
        {
          "actual": 748390.0000000001,
          "pred": 733795.3187691825
        },
        {
          "actual": 1010694.0,
          "pred": 831366.370087131
        },
        {
          "actual": 931727.0000000007,
          "pred": 754553.0757443567
        },
        {
          "actual": 1104066.0000000007,
          "pred": 537073.8043250466
        },
        {
          "actual": 1284608.0000000005,
          "pred": 747481.8779724262
        },
        {
          "actual": 1588000.0000000005,
          "pred": 1440572.7820697825
        }
      ]
    },
    {
      "tax_head": "dt",
      "model": "arimax",
      "h1_smape": 21.03,
      "h3_smape": 31.44,
      "h5_smape": 31.08,
      "mae_pct": 18.19,
      "rmse_pct": 22.33,
      "rmse_pct_abs": 36.66,
      "bias_pct": -22.15,
      "n_test": 14,
      "stability": 0.1295,
      "series": [
        {
          "actual": 743408.9999999994,
          "pred": 720496.8564794494
        },
        {
          "actual": 877255.0,
          "pred": 902662.1354657265
        },
        {
          "actual": 1033720.0000000008,
          "pred": 852462.8645191242
        },
        {
          "actual": 1217473.9999999995,
          "pred": 999680.5396886809
        },
        {
          "actual": 1344226.0000000002,
          "pred": 1194027.5981851765
        },
        {
          "actual": 1536582.9999999995,
          "pred": 1396135.5157291333
        },
        {
          "actual": 1445507.9999999988,
          "pred": 1547635.5580025173
        },
        {
          "actual": 1523444.9999999995,
          "pred": 1736860.5842046265
        },
        {
          "actual": 1731254.000000001,
          "pred": 1584293.827404294
        },
        {
          "actual": 2284915.9999999995,
          "pred": 1659377.8173608058
        },
        {
          "actual": 3270819.9999999977,
          "pred": 1850391.9505128341
        },
        {
          "actual": 4530730.999999999,
          "pred": 2540535.601783477
        },
        {
          "actual": 5791667.000000004,
          "pred": 4062793.3887315285
        },
        {
          "actual": 6901999.999999998,
          "pred": 5601444.87293641
        }
      ]
    },
    {
      "tax_head": "dt",
      "model": "ardl",
      "h1_smape": 22.69,
      "h3_smape": 33.57,
      "h5_smape": 43.04,
      "mae_pct": 19.46,
      "rmse_pct": 23.52,
      "rmse_pct_abs": 34.75,
      "bias_pct": -21.82,
      "n_test": 14,
      "stability": 0.1322,
      "series": [
        {
          "actual": 743408.9999999994,
          "pred": 782804.072875716
        },
        {
          "actual": 877255.0,
          "pred": 910230.1791859273
        },
        {
          "actual": 1033720.0000000008,
          "pred": 819298.7048632571
        },
        {
          "actual": 1217473.9999999995,
          "pred": 853761.0243674278
        },
        {
          "actual": 1344226.0000000002,
          "pred": 1050641.6448763558
        },
        {
          "actual": 1536582.9999999995,
          "pred": 1222580.8416108405
        },
        {
          "actual": 1445507.9999999988,
          "pred": 1404767.5263925907
        },
        {
          "actual": 1523444.9999999995,
          "pred": 1653479.2285679146
        },
        {
          "actual": 1731254.000000001,
          "pred": 1602968.913909426
        },
        {
          "actual": 2284915.9999999995,
          "pred": 1630878.6072091237
        },
        {
          "actual": 3270819.9999999977,
          "pred": 1900089.0530465418
        },
        {
          "actual": 4530730.999999999,
          "pred": 2758605.6891313395
        },
        {
          "actual": 5791667.000000004,
          "pred": 3795864.1718669236
        },
        {
          "actual": 6901999.999999998,
          "pred": 6377818.412614246
        }
      ]
    },
    {
      "tax_head": "dt",
      "model": "enet",
      "h1_smape": 24.55,
      "h3_smape": 36.27,
      "h5_smape": 45.3,
      "mae_pct": 20.79,
      "rmse_pct": 24.98,
      "rmse_pct_abs": 38.36,
      "bias_pct": -26.0,
      "n_test": 14,
      "stability": 0.1384,
      "series": [
        {
          "actual": 743408.9999999994,
          "pred": 738979.8553147964
        },
        {
          "actual": 877255.0,
          "pred": 848429.7588759304
        },
        {
          "actual": 1033720.0000000008,
          "pred": 816469.8982824215
        },
        {
          "actual": 1217473.9999999995,
          "pred": 875574.9061394677
        },
        {
          "actual": 1344226.0000000002,
          "pred": 1010966.716892197
        },
        {
          "actual": 1536582.9999999995,
          "pred": 1100121.6150394098
        },
        {
          "actual": 1445507.9999999988,
          "pred": 1336008.7397025158
        },
        {
          "actual": 1523444.9999999995,
          "pred": 1540530.9977923522
        },
        {
          "actual": 1731254.000000001,
          "pred": 1539107.5023498451
        },
        {
          "actual": 2284915.9999999995,
          "pred": 1686104.20020248
        },
        {
          "actual": 3270819.9999999977,
          "pred": 1929062.9934394986
        },
        {
          "actual": 4530730.999999999,
          "pred": 2448995.992125588
        },
        {
          "actual": 5791667.000000004,
          "pred": 3970821.0134343794
        },
        {
          "actual": 6901999.999999998,
          "pred": 5489744.204636955
        }
      ]
    },
    {
      "tax_head": "fed",
      "model": "arimax",
      "h1_smape": 22.88,
      "h3_smape": 34.94,
      "h5_smape": 42.43,
      "mae_pct": 20.03,
      "rmse_pct": 23.89,
      "rmse_pct_abs": 40.43,
      "bias_pct": -23.25,
      "n_test": 14,
      "stability": 0.1302,
      "series": [
        {
          "actual": 120964.00000000007,
          "pred": 154695.1967417314
        },
        {
          "actual": 138083.99999999997,
          "pred": 105004.5434439063
        },
        {
          "actual": 162248.00000000003,
          "pred": 126883.23293989224
        },
        {
          "actual": 188054.99999999988,
          "pred": 153159.92854487285
        },
        {
          "actual": 197910.99999999997,
          "pred": 176612.594084655
        },
        {
          "actual": 213493.0,
          "pred": 211154.50803846808
        },
        {
          "actual": 238185.99999999994,
          "pred": 184915.05805208103
        },
        {
          "actual": 250474.00000000015,
          "pred": 253039.66670831814
        },
        {
          "actual": 277046.0,
          "pred": 278711.0660572649
        },
        {
          "actual": 320657.99999999977,
          "pred": 218361.58962073925
        },
        {
          "actual": 369885.00000000006,
          "pred": 302643.67076395766
        },
        {
          "actual": 577451.0000000002,
          "pred": 453887.296282279
        },
        {
          "actual": 766641.0000000001,
          "pred": 396381.33499849535
        },
        {
          "actual": 888000.0000000006,
          "pred": 598839.570010139
        }
      ]
    },
    {
      "tax_head": "fed",
      "model": "enet",
      "h1_smape": 25.6,
      "h3_smape": 40.41,
      "h5_smape": 54.51,
      "mae_pct": 22.46,
      "rmse_pct": 24.78,
      "rmse_pct_abs": 38.59,
      "bias_pct": -24.57,
      "n_test": 14,
      "stability": 0.1048,
      "series": [
        {
          "actual": 120964.00000000007,
          "pred": 152909.10979617125
        },
        {
          "actual": 138083.99999999997,
          "pred": 125409.79809422846
        },
        {
          "actual": 162248.00000000003,
          "pred": 117979.39178145285
        },
        {
          "actual": 188054.99999999988,
          "pred": 119283.6861196654
        },
        {
          "actual": 197910.99999999997,
          "pred": 146985.4450577057
        },
        {
          "actual": 213493.0,
          "pred": 174916.92041287915
        },
        {
          "actual": 238185.99999999994,
          "pred": 195872.0454267502
        },
        {
          "actual": 250474.00000000015,
          "pred": 224658.23834039972
        },
        {
          "actual": 277046.0,
          "pred": 257638.2202527956
        },
        {
          "actual": 320657.99999999977,
          "pred": 264029.8355957979
        },
        {
          "actual": 369885.00000000006,
          "pred": 316580.495805224
        },
        {
          "actual": 577451.0000000002,
          "pred": 403752.572925635
        },
        {
          "actual": 766641.0000000001,
          "pred": 424329.77085492975
        },
        {
          "actual": 888000.0000000006,
          "pred": 627887.3031155263
        }
      ]
    },
    {
      "tax_head": "fed",
      "model": "ardl",
      "h1_smape": 26.03,
      "h3_smape": 41.26,
      "h5_smape": 55.87,
      "mae_pct": 22.67,
      "rmse_pct": 25.52,
      "rmse_pct_abs": 41.41,
      "bias_pct": -25.83,
      "n_test": 14,
      "stability": 0.1172,
      "series": [
        {
          "actual": 120964.00000000007,
          "pred": 154359.5533472489
        },
        {
          "actual": 138083.99999999997,
          "pred": 121519.85209261374
        },
        {
          "actual": 162248.00000000003,
          "pred": 118179.32919896934
        },
        {
          "actual": 188054.99999999988,
          "pred": 123156.27818452237
        },
        {
          "actual": 197910.99999999997,
          "pred": 150795.78135443476
        },
        {
          "actual": 213493.0,
          "pred": 196904.79388696287
        },
        {
          "actual": 238185.99999999994,
          "pred": 207491.59613664311
        },
        {
          "actual": 250474.00000000015,
          "pred": 225371.15270839605
        },
        {
          "actual": 277046.0,
          "pred": 255020.0304591957
        },
        {
          "actual": 320657.99999999977,
          "pred": 263844.476956865
        },
        {
          "actual": 369885.00000000006,
          "pred": 295891.7385834458
        },
        {
          "actual": 577451.0000000002,
          "pred": 352295.88490079675
        },
        {
          "actual": 766641.0000000001,
          "pred": 409959.7559880226
        },
        {
          "actual": 888000.0000000006,
          "pred": 617890.1766814016
        }
      ]
    },
    {
      "tax_head": "gst",
      "model": "enet",
      "h1_smape": 7.83,
      "h3_smape": 22.34,
      "h5_smape": 31.93,
      "mae_pct": 8.41,
      "rmse_pct": 11.45,
      "rmse_pct_abs": 11.69,
      "bias_pct": 6.6,
      "n_test": 14,
      "stability": 0.0777,
      "series": [
        {
          "actual": 842527.9999999995,
          "pred": 849040.6576251098
        },
        {
          "actual": 996382.0000000005,
          "pred": 1001564.7355366708
        },
        {
          "actual": 1087789.9999999993,
          "pred": 1140419.3686848392
        },
        {
          "actual": 1302371.0,
          "pred": 1284704.8112830934
        },
        {
          "actual": 1328964.9999999988,
          "pred": 1384068.830365017
        },
        {
          "actual": 1485305.999999999,
          "pred": 1704223.7600082431
        },
        {
          "actual": 1459212.9999999998,
          "pred": 1790569.3797152326
        },
        {
          "actual": 1596877.0000000014,
          "pred": 1928016.9612278044
        },
        {
          "actual": 1988308.000000001,
          "pred": 2146517.4959814157
        },
        {
          "actual": 2532227.9999999995,
          "pred": 2610504.7981811566
        },
        {
          "actual": 2591434.000000002,
          "pred": 2901677.290133098
        },
        {
          "actual": 3086832.0000000014,
          "pred": 3700373.4603874977
        },
        {
          "actual": 3901372.0000000033,
          "pred": 3867468.067538466
        },
        {
          "actual": 4753000.0,
          "pred": 4553127.180503061
        }
      ]
    },
    {
      "tax_head": "gst",
      "model": "ardl",
      "h1_smape": 14.07,
      "h3_smape": 21.23,
      "h5_smape": 33.42,
      "mae_pct": 15.56,
      "rmse_pct": 18.41,
      "rmse_pct_abs": 23.85,
      "bias_pct": 16.86,
      "n_test": 14,
      "stability": 0.0984,
      "series": [
        {
          "actual": 842527.9999999995,
          "pred": 924707.632096265
        },
        {
          "actual": 996382.0000000005,
          "pred": 1055300.1682758117
        },
        {
          "actual": 1087789.9999999993,
          "pred": 1194866.760304711
        },
        {
          "actual": 1302371.0,
          "pred": 1245014.1476247234
        },
        {
          "actual": 1328964.9999999988,
          "pred": 1449932.8576310321
        },
        {
          "actual": 1485305.999999999,
          "pred": 1811127.3612773903
        },
        {
          "actual": 1459212.9999999998,
          "pred": 1852092.4414137148
        },
        {
          "actual": 1596877.0000000014,
          "pred": 2167949.1694463044
        },
        {
          "actual": 1988308.000000001,
          "pred": 2096097.151172053
        },
        {
          "actual": 2532227.9999999995,
          "pred": 2907435.6457375474
        },
        {
          "actual": 2591434.000000002,
          "pred": 2975659.6308254246
        },
        {
          "actual": 3086832.0000000014,
          "pred": 3317469.7098958753
        },
        {
          "actual": 3901372.0000000033,
          "pred": 5143329.084312127
        },
        {
          "actual": 4753000.0,
          "pred": 5693522.38312082
        }
      ]
    },
    {
      "tax_head": "gst",
      "model": "arimax",
      "h1_smape": 14.97,
      "h3_smape": 15.76,
      "h5_smape": 18.8,
      "mae_pct": 16.84,
      "rmse_pct": 21.92,
      "rmse_pct_abs": 37.78,
      "bias_pct": 19.89,
      "n_test": 14,
      "stability": 0.1403,
      "series": [
        {
          "actual": 842527.9999999995,
          "pred": 909837.7534566375
        },
        {
          "actual": 996382.0000000005,
          "pred": 1032461.9801894805
        },
        {
          "actual": 1087789.9999999993,
          "pred": 1254682.5066179417
        },
        {
          "actual": 1302371.0,
          "pred": 1390992.8496055303
        },
        {
          "actual": 1328964.9999999988,
          "pred": 1382111.1361523224
        },
        {
          "actual": 1485305.999999999,
          "pred": 1549925.259793625
        },
        {
          "actual": 1459212.9999999998,
          "pred": 1683292.9213454619
        },
        {
          "actual": 1596877.0000000014,
          "pred": 1903778.545057651
        },
        {
          "actual": 1988308.000000001,
          "pred": 1862281.5301743338
        },
        {
          "actual": 2532227.9999999995,
          "pred": 2185771.836957664
        },
        {
          "actual": 2591434.000000002,
          "pred": 2934314.7312041763
        },
        {
          "actual": 3086832.0000000014,
          "pred": 4394098.684281007
        },
        {
          "actual": 3901372.0000000033,
          "pred": 5712245.81843097
        },
        {
          "actual": 4753000.0,
          "pred": 6516475.980297854
        }
      ]
    }
  ],
  "data_span": {
    "start": "1995",
    "end": "2026",
    "n": 31
  }
}